LICENSE.txt
MANIFEST.in
README.rst
setup.cfg
setup.py
error_tracker/__init__.py
error_tracker.egg-info/PKG-INFO
error_tracker.egg-info/SOURCES.txt
error_tracker.egg-info/dependency_links.txt
error_tracker.egg-info/not-zip-safe
error_tracker.egg-info/requires.txt
error_tracker.egg-info/top_level.txt
error_tracker/django/__init__.py
error_tracker/django/admin.py
error_tracker/django/apps.py
error_tracker/django/middleware.py
error_tracker/django/models.py
error_tracker/django/settings.py
error_tracker/django/urls.py
error_tracker/django/utils.py
error_tracker/django/views.py
error_tracker/django/migrations/0001_initial.py
error_tracker/django/migrations/0002_auto_20201018_1311.py
error_tracker/django/migrations/__init__.py
error_tracker/django/templates/error_tracker/base.html
error_tracker/django/templates/error_tracker/detail.html
error_tracker/django/templates/error_tracker/list.html
error_tracker/django/templates/error_tracker/admin/change_form.html
error_tracker/django/templates/error_tracker/partials/navigation.html
error_tracker/django/templates/error_tracker/partials/partial_table.html
error_tracker/django/templatetags/__init__.py
error_tracker/django/templatetags/error_tracker.py
error_tracker/flask/__init__.py
error_tracker/flask/defaults.py
error_tracker/flask/flask_error.py
error_tracker/flask/utils.py
error_tracker/flask/view.py
error_tracker/flask/templates/error_tracker/base.html
error_tracker/flask/templates/error_tracker/detail.html
error_tracker/flask/templates/error_tracker/list.html
error_tracker/libs/__init__.py
error_tracker/libs/exception_formatter.py
error_tracker/libs/mixins.py
error_tracker/libs/utils.py