Metadata-Version: 2.1
Name: error-tracker
Version: 3.1.1
Summary: Simple and Extensible Error Monitoring/Tracking framework for Python
Home-page: https://github.com/sonus21/error-tracker/
Author: Sonu Kumar
Author-email: sonunitw12@gmail.com
License: BSD-3-Clause
Keywords: Flask,error-tracker,exception-tracking,exception-monitoring,Django
Platform: any
Classifier: Development Status :: 5 - Production/Stable
Classifier: Environment :: Web Environment
Classifier: Intended Audience :: Developers
Classifier: License :: OSI Approved :: BSD License
Classifier: Operating System :: OS Independent
Classifier: Programming Language :: Python
Classifier: Programming Language :: Python :: 2.7
Classifier: Programming Language :: Python :: 3.5
Classifier: Programming Language :: Python :: 3.6
Classifier: Programming Language :: Python :: 3.7
Classifier: Programming Language :: Python :: 3.8
Classifier: Programming Language :: Python :: 3.9
Classifier: Programming Language :: Python :: 3.10
Classifier: Topic :: Software Development :: Libraries :: Python Modules
Requires-Python: >=2.7, !=3.0.*, !=3.1.*, !=3.2.*, !=3.3.*, !=3.4.*
Provides-Extra: Django
Provides-Extra: DRF
Provides-Extra: Flask
License-File: LICENSE.txt
